roam_to_git/__init__.py
roam_to_git/__main__.py
roam_to_git/formatter.py
roam_to_git/fs.py
roam_to_git/scrapping.py
roam_to_git-0.2.1.dist-info/entry_points.txt
roam_to_git-0.2.1.dist-info/LICENSE.txt
roam_to_git-0.2.1.dist-info/WHEEL
roam_to_git-0.2.1.dist-info/METADATA
roam_to_git-0.2.1.dist-info/RECORD
