Metadata-Version: 2.1
Name: roam-to-git
Version: 0.2.1
Summary: Automatic RoamResearch backup to Git
Home-page: https://github.com/MatthieuBizien/roam-to-git
License: Matthieu Bizien <oao2005@gmail.com>
Keywords: RoamResearch,Roam
Author: Matthieu Bizien
Author-email: matthieu@yokai.ai
Requires-Python: >=3.6,<4.0
Classifier: License :: Other/Proprietary License
Classifier: Programming Language :: Python :: 3
Classifier: Programming Language :: Python :: 3.6
Classifier: Programming Language :: Python :: 3.7
Classifier: Programming Language :: Python :: 3.8
Classifier: Programming Language :: Python :: 3.9
Provides-Extra: test
Requires-Dist: GitPython (>=3.1.14,<4.0.0)
Requires-Dist: loguru (>=0.5.3,<0.6.0)
Requires-Dist: mypy (>=0.812,<0.813); extra == "test"
Requires-Dist: pathvalidate (>=2.3.2,<3.0.0)
Requires-Dist: psutil (>=5.8.0,<6.0.0)
Requires-Dist: python-dotenv (>=0.15.0,<0.16.0)
Requires-Dist: selenium (>=3.141.0,<4.0.0)
